flyteplugins/spark/__init__.py
flyteplugins/spark/df_transformer.py
flyteplugins/spark/task.py
flyteplugins_spark-2.0.0b53.dist-info/METADATA
flyteplugins_spark-2.0.0b53.dist-info/WHEEL
flyteplugins_spark-2.0.0b53.dist-info/top_level.txt
flyteplugins_spark-2.0.0b53.dist-info/RECORD
