Metadata-Version: 2.4
Name: flyteplugins-spark
Version: 2.0.0b53
Summary: Spark plugin for flyte
Author-email: Kevin Su <pingsutw@users.noreply.github.com>
Requires-Python: >=3.10
Requires-Dist: pyspark
Requires-Dist: flyte
